gurun/__init__.py
gurun/cv/__init__.py
gurun/cv/detection.py
gurun/cv/transformation.py
gurun/cv/utils.py
gurun/exceptions.py
gurun/gui/__init__.py
gurun/gui/io.py
gurun/gui/os.py
gurun/gui/screenshot.py
gurun/node.py
gurun/runner.py
gurun/utils.py
gurun-1.1.0.dist-info/LICENSE
gurun-1.1.0.dist-info/WHEEL
gurun-1.1.0.dist-info/METADATA
gurun-1.1.0.dist-info/RECORD
