Metadata-Version: 2.1
Name: gurun
Version: 1.1.0
Summary: Task automation framework
Home-page: https://github.com/gabrielguarisa/gurun
License: MIT
Keywords: automation,workflow,pipeline,task,framework
Author: Gabriel Guarisa
Author-email: gabrielguarisa@gmail.com
Requires-Python: >=3.7.12,<3.11
Classifier: Development Status :: 3 - Alpha
Classifier: Intended Audience :: Developers
Classifier: License :: OSI Approved :: MIT License
Classifier: Operating System :: OS Independent
Classifier: Programming Language :: Python :: 3
Classifier: Programming Language :: Python :: 3.10
Classifier: Programming Language :: Python :: 3.8
Classifier: Programming Language :: Python :: 3.9
Classifier: Topic :: Software Development :: Libraries :: Python Modules
Provides-Extra: cv
Provides-Extra: full
Provides-Extra: gui
Requires-Dist: PyAutoGUI (>=0.9.41,<0.10.0); extra == "gui" or extra == "full"
Requires-Dist: mss (>=6.1.0,<7.0.0); extra == "gui" or extra == "full"
Requires-Dist: opencv-python (>=4.5.4,<5.0.0); extra == "gui" or extra == "cv" or extra == "full"
Project-URL: Repository, https://github.com/gabrielguarisa/gurun
